{
  "id": 46862,
  "회사이름": "<a>유클리드소프트</a>",
  "회사제목": "<h2>[플랫폼개발팀] 웹개발자</h2>",
  "회사설명": "<span>• AI 데이터 품질 및 분석 플랫폼 구현 및 관리\n• Python 기반의 웹사이트 운영 및 빅데이터 핸들링\n• React 또는 Boostrap 기반의 프론트엔드 사이트 개발\n• Kotlin 베이스의 Springboot 사이트 개발</span>",
  "주요업무": "span• 분석모듈의 입출력 설계에 따른 분석 모듈 호출 및 실행 관리\n• 대용량 데이터 핸들링 및 통계분석 시각화 개발\n• 데이터 라벨링을 위한 저작도구 개발",
  "자격요건": "span• 컴퓨터 관련 전공 졸업 또는 졸업예정의 신입 지원자\n• 경력 3년 이내 웹개발(Django, Springboot, React 등) 지원자\n• RDBMS(MySQL 또는 Mariadb 등) 경험자",
  "우대사항": "span• 인공지능 모델(자연어 또는 비전) 학습 및 추론 경험자\n• 컴퓨터 관련 전공자 우대(컴퓨터 공학 및 빅데이터 등)\n• 관련 자격증 소지자 우대(정보처리 기사 등)\n• Elasticsearch, Redis등 경험자\n• Kotlin 베이스의 Springboot 경험자",
  "혜택 및 복지": "span• 주 5일제 근무 및 연차 및 하계휴가 제도\n• 퇴직연금 제도 운영\n• 워크샵 및 각종 팀별 단합 행사 지원\n• Jetbrain 베이스의 통합 IDE 지원",
  "기술스택": "Github,Linux,MySQL,React,HTML,JavaScript,Kotlin,Python,AWS,Spring Framework,"
}