{
  "id": 217430,
  "CompanyName": "위메이드",
  "Pay": [
    8000,
    12000
  ],
  "Career": [
    5,
    10
  ],
  "Stacks": [],
  "Job": [
    "시스템/네트워크",
    " 시스템 소프트웨어"
  ],
  "MainData": "<div class=\"yO7TZRtCO7sznD0Csuw_\"><section><h5 class=\"M7i0c3SgWr1QMhIricKz\">업무 소개</h5><div class=\"markdown\"><div class=\"toastui-editor-contents\" style=\"overflow-wrap: break-word;\"><p data-nodeid=\"1\">위메이드는 20여년간 게임 사업에서 그 명성을 유지하며 활약하고 있습니다.</p>\n<p data-nodeid=\"2\">우리는 게임을 기반으로 다양한 문화 영역에서 무한한 상상을 현실로 만드는 창조 집단으로서 훌륭한 프로 의식, 인격, 열정을 갖춘 인재들이 모여 있습니다.</p>\n<p data-nodeid=\"3\">미르4를 성공적으로 출시하여 게임업계에 “Play to Earn”이라는 새로운 패러다임을 이끌었습니다.</p>\n<p data-nodeid=\"4\">또한, 블록체인 선두주자로서 자체 메인넷 WEMIX3.0과 블록체인 게이밍 플랫폼 WEMIX Play, NFT와 DAO 플랫폼인 Nile, Defi 플랫폼 WEMIX.Fi를 통해 <span class=\"highlight\" style=\"background-color:transparent\">블록체인 생태계 구축에 박차를 가하고 있습니다.</span></p>\n<p data-nodeid=\"5\">이외에도 위메이드그룹은 IP확장 및 메타버스 등의 미래사업에 대한 공격적인 투자활동과 사업다각화를 적극 추진하며 독보적인 성장을 하고 있는 <span class=\"highlight\" style=\"background-color:transparent\">글로벌 종합 플랫폼 기업입니다.</span></p>\n<p data-nodeid=\"6\">우리는 각자의 분야에서 최고가 되기 위한 꿈과 열정을 지니고, 맡은 미션을 훌륭하게 수행하여<br/>\n단순한 결과가 아닌 멋진 성과를 보여주고 있습니다.<br/>\n또한 서로에 대한 믿음으로 팀워크와 협업의 시너지를 창출하는 최고의 파트너로 활약하고 있습니다.</p>\n<p data-nodeid=\"7\">무한한 상상력을 현실로 만드는 위메이드 그룹과 함께 하실 분은 지원해주세요.</p>\n<p data-nodeid=\"8\"><span class=\"colour\" style=\"color:rgb(38, 55, 71)\">회사에 입사하면 우리가 함께하게 될 업무는 이렇습니다.</span></p>\n<ul data-nodeid=\"9\">\n<li data-nodeid=\"10\">\n<p data-nodeid=\"11\">사내 서버실(물리 / VM / STORAGE) 구성 운영 관리</p>\n</li>\n<li data-nodeid=\"12\">\n<p data-nodeid=\"13\">사내 네트워크(B.B / L3 / SW) 구성 운영 관리</p>\n</li>\n<li data-nodeid=\"14\">\n<p data-nodeid=\"15\">클라우드 서비스(Azure / AWS / GCP) 구성 운영 관리</p>\n</li>\n<li data-nodeid=\"16\">\n<p data-nodeid=\"17\">백오피스(AD / GWS / 사내 메신저) 기술 지원 및 운영 관리</p>\n</li>\n<li data-nodeid=\"18\">\n<p data-nodeid=\"19\">IT 유/무형 자산 관리 (구매,정산, 실사)</p>\n</li>\n<li data-nodeid=\"20\">\n<p data-nodeid=\"21\">대/내외 IT 통합 계약 수행 및 정산 관리</p>\n</li>\n</ul>\n</div></div></section><section><h5 class=\"M7i0c3SgWr1QMhIricKz\">자격 조건</h5><div class=\"markdown\"><div class=\"toastui-editor-contents\" style=\"overflow-wrap: break-word;\"><ul data-nodeid=\"48\">\n<li data-nodeid=\"49\">\n<p data-nodeid=\"50\">경력 5-10년차</p>\n</li>\n<li data-nodeid=\"51\">\n<p data-nodeid=\"52\">네트워크 (B.B / L3 / SW) 설정 가능자</p>\n</li>\n<li data-nodeid=\"53\">\n<p data-nodeid=\"54\">AD 운영 관리 경험자</p>\n</li>\n<li data-nodeid=\"55\">\n<p data-nodeid=\"56\">클라우드(Azure / AWS / GCP) 구축 가능자</p>\n</li>\n</ul>\n</div></div></section><section><h5 class=\"M7i0c3SgWr1QMhIricKz\">우대사항</h5><div class=\"markdown\"><div class=\"toastui-editor-contents\" style=\"overflow-wrap: break-word;\"><ul data-nodeid=\"61\">\n<li data-nodeid=\"62\"></li>\n</ul>\n</div></div></section><section><!--v-if--><div class=\"markdown\"><div class=\"toastui-editor-contents\" style=\"overflow-wrap: break-word;\"><p data-nodeid=\"63\"><span class=\"colour\" style=\"color:black\"><strong data-nodeid=\"106\">[전형절차]</strong></span><br/>\n<span class=\"colour\" style=\"color:black\">서류전형 - 실무면접 - 임원면접 - 최종합격</span><br/>\n*서류전형의 경우, 합격자 분들에 한하여 개별 안내드립니다.<br/>\n<span class=\"colour\" style=\"color:black\">*직무에 따라 면접 전형 전후로 과제 전형이 추가될 수 있습니다.</span><br/>\n<span class=\"colour\" style=\"color:black\">*면접결과 확정 및 처우협의(입사일 포함) 완료 후 최종합격이 결정됩니다.</span><br/>\n<span class=\"colour\" style=\"color:black\">*본 공고는 적격자 채용 시 마감될 수 있음을 알려드립니다.</span><br/>\n<span class=\"colour\" style=\"color:black\">*장애인, 국가보훈대상자는 관계 법령에 의거하여 우대합니다.</span><br/>\n<span class=\"colour\" style=\"color:black\">*</span><span class=\"colour\" style=\"color:black\">지원서 내용이 사실과 다를 경우 합격 및 입사가 취소 될 수 있습니다.</span></p>\n<p data-nodeid=\"64\"><span class=\"colour\" style=\"color:rgb(38, 55, 71)\"><strong data-nodeid=\"162\">[혜택 및 복지]</strong></span><br/>\n<span class=\"colour\" style=\"color:black\">• 배려와 존중으로 함께 일하는 최고의 팀 동료들이 있어요</span><br/>\n<span class=\"colour\" style=\"color:black\">• 취향에 따라, 기분에 따라 마음에 드는 메뉴를 선택하실 수 있도록 식사포인트를 지원해 드려요</span><br/>\n<span class=\"colour\" style=\"color:black\">• 최상의 원두와 전문 바리스타가 있는 카페테리아에서 언제든 커피 혹은 음료는 무료로 마음껏 드세요</span><br/>\n<span class=\"colour\" style=\"color:black\">• 수면실, 샤워룸, 수유실, 스포츠센터 등 위메이드인들을 위한 다양한 편의시설도 있어요</span><br/>\n<span class=\"colour\" style=\"color:black\">• 연간 200만원 지급되는 복지포인트로 다양한 문화 혹은 취미 생활 누리세요</span><br/>\n<span class=\"colour\" style=\"color:black\">• 일과 생활의 균형을 위해 자유롭게 연차를 사용하세요</span><br/>\n<span class=\"colour\" style=\"color:black\">• 다양한 경조사에 대한 경조 지원금, 유급휴가를 지원해 드려요</span><br/>\n<span class=\"colour\" style=\"color:black\">• 단체보험가입, 종합건강검진, 독감예방접종 지원받으시고 건강도 챙기면서 일해요</span><br/>\n<span class=\"colour\" style=\"color:black\">• 가족의 종합건강검진도 함께 챙겨요</span><br/>\n<span class=\"colour\" style=\"color:black\">• 자녀의 진학에 부담갖지 않으시길 바라며 입학축하금 및 대학교 학자금을 지원해 드려요</span><br/>\n<span class=\"colour\" style=\"color:black\">• 열일 후 달콤한 휴식을 위해 레지던스 및 리조트회원권을 준비했어요</span><br/>\n<span class=\"colour\" style=\"color:black\">• 위메이드에서 오래도록 기여해주신 장기근속 위메이드인에게는 포상금을 지급해요</span></p>\n</div></div></section><!--v-if--><!--v-if--></div>",
  "WorkLocation": "경기도 성남시 분당구 대왕판교로644번길 49, 2층 201호 전체(삼평동, 코리아벤처타운)",
  "DeadLind": "23년 04월 30일 23:59까지",
  "시간": "23-03-18 17:14:26"
}