{
  "id": 3945,
  "회사이름": "<a>비트코퍼레이션</a>",
  "회사제목": "<h1>프론트엔드 개발자 모집</h1>",
  "본문": "None",
  "경력": "4 - 6년",
  "학력": "대학졸업(2,3년) 이상",
  "마감일": "상시",
  "근무지역": "경기도 성남시 분당구 분당로 55, 9층\n지도보기·주소복사",
  "기술스택": "JavaScript,React,HTML5,CSS 3,REST API,AWS,React Native,",
  "기업/서비스 소개": "비트코퍼레이션은 F&B의 가치를 넘어 커피라는 콘텐츠로 푸드테크 플랫폼을 만듭니다.\n첨단 기술을 활용한 로봇 카페 비트는 미래지향적이고 혁신적인 새로운 카페 스타일을 제안합니다.\n\n지금까지의 카페들이 복잡한 내연기관을 가진 내연기관 자동차로 구분된다면, 비트는 복잡한 요소가 줄어든 전기 자동차로 비유되고 싶습니다.\n\n비트코퍼레이션은 단순한 카페에서 벗어나 국내 카페 시장의 새로운 패러다임으로 글로벌 푸드테크 비즈니스의 미래를 제시합니다.\n또한, 비트코퍼레이션은 Retail 시장에서 우리의 데일리 라이프와 함께하는 F&B(Food & Beverage) 컨텐츠를 다양한 기술로 해석하고, 보다 즐거운 경험을 하실 수 있도록 끊임없는 고민과 노력을 기울이고 있습니다.\n\nRobotics, IoT, RPA, DI 등 다양한 응용 기술을 통해, 더욱 편하고 자유로운 라이프를 즐길 수 있는 세상을 만드는 것이 저희의 목표입니다.\n\n푸드테크라는 새로운 신성장산업 분야를 리드하고 있는 비트코퍼레이션은 비대면 시대에 맞추어,\n푸드테크 비즈니스의 표준을 만들고 새로운 미래를 제시하려 합니다.",
  "취업축하금": "💰 취업축하금 70만원"
}